prestashop_gateway/__init__.py
prestashop_gateway/connection.py
prestashop_gateway/error.py
prestashop_gateway/exception.py
prestashop_gateway-1.3.1598471715.dist-info/LICENSE
prestashop_gateway-1.3.1598471715.dist-info/METADATA
prestashop_gateway-1.3.1598471715.dist-info/WHEEL
prestashop_gateway-1.3.1598471715.dist-info/top_level.txt
prestashop_gateway-1.3.1598471715.dist-info/RECORD
