Metadata-Version: 2.1
Name: prestashop-gateway
Version: 1.3.1598471715
Summary: Python gateway to call Prestashop Webservice
Home-page: https://gitlab.com/eGenGuru/prestashop_gateway/-/wikis/Home
Author: Eric Laugier
Author-email: eric.laugier@egen.guru
License: GNU Lesser General Public License v3 (LGPLv3)
Platform: UNKNOWN
Classifier: Development Status :: 3 - Alpha
Classifier: License :: OSI Approved :: GNU Lesser General Public License v3 (LGPLv3)
Classifier: Operating System :: OS Independent
Classifier: Programming Language :: Python
Classifier: Programming Language :: Python :: 3
Classifier: Programming Language :: Python :: 3 :: Only
Classifier: Programming Language :: Python :: 3.6
Classifier: Programming Language :: Python :: 3.7
Classifier: Programming Language :: Python :: 3.8
Classifier: Topic :: Internet :: WWW/HTTP
Classifier: Topic :: Internet :: WWW/HTTP :: Dynamic Content
Requires-Dist: appdirs (==1.4.4)
Requires-Dist: attrs (==19.3.0)
Requires-Dist: black (==19.10b0)
Requires-Dist: certifi (==2020.6.20)
Requires-Dist: chardet (==3.0.4)
Requires-Dist: click (==7.1.2)
Requires-Dist: idna (==2.10)
Requires-Dist: pathspec (==0.8.0)
Requires-Dist: regex (==2020.7.14)
Requires-Dist: requests (==2.24.0)
Requires-Dist: toml (==0.10.1)
Requires-Dist: typed-ast (==1.4.1)
Requires-Dist: urllib3 (==1.25.10)
Requires-Dist: xmltodict (==0.12.0)
